b3_greet/__init__.py
b3_greet-0.1.1.dist-info/LICENSE
b3_greet-0.1.1.dist-info/METADATA
b3_greet-0.1.1.dist-info/WHEEL
b3_greet-0.1.1.dist-info/top_level.txt
b3_greet-0.1.1.dist-info/RECORD
