Metadata-Version: 2.1
Name: b3_greet
Version: 0.1.1
Summary: A simple greeting library
Home-page: https://github.com/BlueBirdBack/b3_greet
Author: Avery
Author-email: avery@bluebirdback.com
Classifier: Programming Language :: Python :: 3
Classifier: License :: OSI Approved :: MIT License
Classifier: Operating System :: OS Independent
Requires-Python: >=3.6
License-File: LICENSE
